diario/__init__.py
diario/admin.py
diario-0.2.1.dist-info/LICENSE
diario-0.2.1.dist-info/METADATA
diario-0.2.1.dist-info/WHEEL
diario-0.2.1.dist-info/top_level.txt
diario-0.2.1.dist-info/RECORD
