Metadata-Version: 2.1
Name: diario
Version: 0.2.1
Summary: DIARIO SDK
Home-page: https://diario.e-paths.com/index.html
Author: ElevenPaths
Author-email: innovationlab@11paths.com
License: UNKNOWN
Keywords: sdk,api,diario
Platform: UNKNOWN
Classifier: Intended Audience :: Developers
Classifier: Operating System :: OS Independent
Classifier: Programming Language :: Python
Classifier: Programming Language :: Python :: 2.7
Classifier: Programming Language :: Python :: 3
License-File: LICENSE
Requires-Dist: sdklib (==1.10.3)
Requires-Dist: PySocks
